CustomCTkDialog/__init__.py
CustomCTkDialog/custom_ctk_dialog.py
CustomCTkDialog/electron_loader.py
CustomCTkDialog/py.typed
customctkdialog-0.2.6.dist-info/METADATA
customctkdialog-0.2.6.dist-info/WHEEL
customctkdialog-0.2.6.dist-info/top_level.txt
customctkdialog-0.2.6.dist-info/RECORD
