Metadata-Version: 2.4
Name: customctkdialog
Version: 0.2.6
Summary: A custom dialog component for CustomTkinter
Author-email: AceBurgundy <Samadriansabalo99@gmail.com>
Project-URL: Homepage, https://github.com/AceBurgundy/CustomCTkDialog
Project-URL: Repository, https://github.com/AceBurgundy/CustomCTkDialog
Requires-Python: >=3.11
Requires-Dist: customtkinter>=5.2.2
Requires-Dist: pillow>=12.0.0
Requires-Dist: requests>=2.32.5
